mech/__init__.py
mech/__main__.py
mech/command.py
mech/docopt.py
mech/mech.py
mech/utils.py
mech/vmrun.py
mech-0.6.dist-info/DESCRIPTION.rst
mech-0.6.dist-info/METADATA
mech-0.6.dist-info/RECORD
mech-0.6.dist-info/WHEEL
mech-0.6.dist-info/entry_points.txt
mech-0.6.dist-info/metadata.json
mech-0.6.dist-info/top_level.txt
