Metadata-Version: 2.0
Name: mech
Version: 0.6
Summary: Tool for command line virtual machines
Home-page: https://github.com/mechboxes/mech
Author: Kevin Chung
Author-email: kchung@nyu.edu
License: UNKNOWN
Download-URL: https://github.com/mechboxes/mech/tarball/master
Keywords: vagrant,vmware,vmrun,tool,virtualization
Platform: UNKNOWN
Requires-Dist: requests
Requires-Dist: clint
Requires-Dist: docopt
Requires-Dist: filelock
